streamline_logger/__init__.py
streamline_logger/main.py
streamline_logger-0.1.2.dist-info/METADATA
streamline_logger-0.1.2.dist-info/WHEEL
streamline_logger-0.1.2.dist-info/RECORD
