Metadata-Version: 2.1
Name: streamline_logger
Version: 0.1.2
Summary: 
Author: Eric Hasegawa
Author-email: erichasegawa1@gmail.com
Requires-Python: ==3.11.4
Classifier: Programming Language :: Python :: 3
Requires-Dist: boto3 (>=1.28.54,<2.0.0)
Requires-Dist: pydantic (>=2.4.1,<3.0.0)
Requires-Dist: sentry-sdk (>=1.31.0,<2.0.0)
